DAY7/day7.v
module day7 (clk,reset,lfsr_o);
input     wire      clk;
  input     wire      reset;

  output    reg[3:0] lfsr_o;


  always @(posedge clk or posedge reset)
    if (reset)
      lfsr_o <= 4'hA;
    else
      lfsr_o <= {lfsr_o[2:0], lfsr_o[1] ^ lfsr_o[3]};

endmodule

DAY7/day7_tb.v
module day7_tb();

  reg clk;
  reg reset;
  wire [3:0] lfsr_o;

  // Instantiate the DUT (Design Under Test)
  day7 dut (
    .clk(clk),
    .reset(reset),
    .lfsr_o(lfsr_o)
  );

    always #5 clk = ~clk;  // Clock generation
  initial begin
    clk = 0;
    reset = 0;
    #10 reset = 1;
    #15;
    reset=0;
    #100;
    reset=1;
    #100;
    $finish;
  end

   initial begin
    $dumpfile("day7.vcd");
    $dumpvars(0, day7_tb);
  end

  

endmodule

DAY7/day7.vcd
$date
	Thu Aug 24 13:11:59 2023
$end
$version
	Icarus Verilog
$end
$timescale
	1s
$end
$scope module day7_tb $end
$var wire 4 ! lfsr_o [3:0] $end
$var reg 1 " clk $end
$var reg 1 # reset $end
$scope module dut $end
$var wire 1 " clk $end
$var wire 1 # reset $end
$var reg 4 $ lfsr_o [3:0] $end
$upscope $end
$upscope $end
$enddefinitions $end
#0
$dumpvars
bx $
0#
0"
bx !
$end
#5
1"
#10
b1010 !
b1010 $
0"
1#
#15
1"
#20
0"
#25
b100 !
b100 $
1"
0#
#30
0"
#35
b1000 !
b1000 $
1"
#40
0"
#45
b1 !
b1 $
1"
#50
0"
#55
b10 !
b10 $
1"
#60
0"
#65
b101 !
b101 $
1"
#70
0"
#75
b1010 !
b1010 $
1"
#80
0"
#85
b100 !
b100 $
1"
#90
0"
#95
b1000 !
b1000 $
1"
#100
0"
#105
b1 !
b1 $
1"
#110
0"
#115
b10 !
b10 $
1"
#120
0"
#125
b1010 !
b1010 $
1"
1#
